londonaicentre_oncoschema-2.0.1.dist-info/licenses/LICENSE.md
oncoschema/__init__.py
oncoschema/prompt_builder.py
oncoschema/prompt_datagen.txt
oncoschema/prompt_main.txt
oncoschema/py.typed
oncoschema/schema.py
oncoschema/examples/example.json
londonaicentre_oncoschema-2.0.1.dist-info/METADATA
londonaicentre_oncoschema-2.0.1.dist-info/WHEEL
londonaicentre_oncoschema-2.0.1.dist-info/top_level.txt
londonaicentre_oncoschema-2.0.1.dist-info/RECORD
