Metadata-Version: 2.4
Name: londonaicentre-oncoschema
Version: 2.0.1
Summary: Oncology extraction schema for MESA
Author-email: "Dr. Joe Zhang" <jzhang@nhs.net>, "Dr. Martin Chapman" <martin.chapman@nhs.net>, "Dr. Lawrence Adams" <lawrence.adams2@nhs.net>
License-Expression: LicenseRef-Proprietary
Requires-Python: >=3.12
License-File: LICENSE.md
Requires-Dist: pydantic>=2.12.5
Requires-Dist: londonaicentre-mesa-utils>=1.0.0
Dynamic: license-file
